cm_mlperf/__init__.py
cm_mlperf-0.0.0.1.dist-info/LICENSE
cm_mlperf-0.0.0.1.dist-info/METADATA
cm_mlperf-0.0.0.1.dist-info/WHEEL
cm_mlperf-0.0.0.1.dist-info/top_level.txt
cm_mlperf-0.0.0.1.dist-info/RECORD
